{"cameraMode":{"drawMode":0,"name":"Shaded","section":"Shading Mode"},"sceneLighting":true,"audioPlay":false,"sceneViewState":{"m_AlwaysRefresh":false,"showFog":true,"showSkybox":true,"showFlares":true,"showImageEffects":true,"showParticleSystems":true,"showVisualEffectGraphs":true,"m_FxEnabled":true},"in2DMode":false,"pivot":{"x":0.36748552322387698,"y":-0.09511128813028336,"z":0.5277231335639954},"rotation":{"x":0.09765396267175675,"y":-0.010141650214791298,"z":0.0010223337449133397,"w":0.9952038526535034},"size":4.4349775314331059,"orthographic":false}