{"cameraMode":{"drawMode":0,"name":"Shaded","section":"Shading Mode"},"sceneLighting":true,"audioPlay":false,"sceneViewState":{"m_AlwaysRefresh":false,"showFog":true,"showSkybox":true,"showFlares":true,"showImageEffects":true,"showParticleSystems":true,"showVisualEffectGraphs":true,"m_FxEnabled":true},"in2DMode":false,"pivot":{"x":-3.05369234085083,"y":0.16762308776378632,"z":1.3731917142868043},"rotation":{"x":-0.1299164891242981,"y":0.7655186057090759,"z":-0.16341261565685273,"w":-0.608605146408081},"size":6.664318084716797,"orthographic":false}